chiralfinder/__init__.py
chiralfinder/_quadrupole/__init__.py
chiralfinder/_quadrupole/quadrupole_center.py
chiralfinder/_quadrupole/quadrupole_utils.py
chiralfinder/_quadrupole/quadrupole_v1.py
chiralfinder/_quadrupole/quadrupole_v2.py
chiralfinder/_quadrupole/quadrupole_v3.py
chiralfinder/_quadrupole/quadrupole_v4.py
chiralfinder/_quadrupole/quadrupole_v5.py
chiralfinder/_quadrupole/quadrupole_v6.py
chiralfinder/_quadrupole/run.py
chiralfinder-0.1.4.dist-info/entry_points.txt
chiralfinder-0.1.4.dist-info/LICENSE
chiralfinder-0.1.4.dist-info/METADATA
chiralfinder-0.1.4.dist-info/WHEEL
chiralfinder-0.1.4.dist-info/RECORD
