Metadata-Version: 2.1
Name: chiralfinder
Version: 0.1.4
Summary: The chiralfinder package.
Home-page: https://github.com/Meteor-han/chiralfinder/
License: MIT
Keywords: Chirality,Chiral axis
Author: Runhan Shi
Author-email: han.run.jiangming@sjtu.edu.cn
Maintainer: Runhan Shi
Maintainer-email: han.run.jiangming@sjtu.edu.cn
Requires-Python: >=3.8,<4.0
Classifier: License :: OSI Approved :: MIT License
Classifier: Programming Language :: Python :: 3
Classifier: Programming Language :: Python :: 3.8
Classifier: Programming Language :: Python :: 3.9
Classifier: Programming Language :: Python :: 3.10
Classifier: Programming Language :: Python :: 3.11
Classifier: Programming Language :: Python :: 3.12
Classifier: Programming Language :: Python :: 3.13
Requires-Dist: numpy (>=1.26.4,<2.0.0)
Requires-Dist: rdkit (>=2024.3.3,<2025.0.0)
Requires-Dist: tqdm (>=4.65.0,<5.0.0)
Project-URL: Documentation, https://github.com/Meteor-han/chiralfinder/
Project-URL: Repository, https://github.com/Meteor-han/chiralfinder/
Project-URL: issues, https://github.com/Meteor-han/chiralfinder/issues
